pyexam/__init__.py
pyexam/__main__.py
pyexam/exam.py
pyexam/exceptions.py
pyexam/exporter.py
pyexam/loader.py
pyexam/py.typed
pyexam/questions/__init__.py
pyexam/questions/fill_in.py
pyexam/questions/long_answer.py
pyexam/questions/multiple_choice.py
pyexam/questions/parts.py
pyexam/questions/question.py
pyexam/templates/exam.j2
pyexam/templates/fill-in.j2
pyexam/templates/long-answer.j2
pyexam/templates/multiple-choice.j2
pyexam/templates/parts.j2
pyexam/templates/question.j2
pyexam/templates/render-questions.j2
pyexam-0.2.0.dist-info/METADATA
pyexam-0.2.0.dist-info/WHEEL
pyexam-0.2.0.dist-info/entry_points.txt
pyexam-0.2.0.dist-info/licenses/LICENSE
pyexam-0.2.0.dist-info/RECORD
