Metadata-Version: 2.4
Name: pyexam
Version: 0.2.0
Summary: Convert simple YAML documents to LaTeX and PDF exams
License: MIT
License-File: LICENSE
Keywords: exam,latex,pdf,template,yaml
Author: Rui Almeida
Author-email: ruial@outlook.com
Requires-Python: >=3.11
Classifier: License :: OSI Approved :: MIT License
Classifier: Programming Language :: Python :: 3
Classifier: Programming Language :: Python :: 3.11
Classifier: Programming Language :: Python :: 3.12
Classifier: Programming Language :: Python :: 3.13
Classifier: Programming Language :: Python :: 3.14
Requires-Dist: jinja2 (>=3.0.0,<4.0.0)
Requires-Dist: pydantic (>=2.0.0,<3.0.0)
Requires-Dist: pyyaml (>=6.0.0,<7.0.0)
Project-URL: Homepage, https://github.com/ruial/pyexam
Project-URL: Repository, https://github.com/ruial/pyexam
